django_spire/__init__.py
django_spire/conf.py
django_spire/consts.py
django_spire/exceptions.py
django_spire/settings.py
django_spire/urls.py
django_spire/utils.py
django_spire/ai/__init__.py
django_spire/ai/admin.py
django_spire/ai/apps.py
django_spire/ai/decorators.py
django_spire/ai/mixins.py
django_spire/ai/models.py
django_spire/ai/urls.py
django_spire/ai/chat/__init__.py
django_spire/ai/chat/admin.py
django_spire/ai/chat/apps.py
django_spire/ai/chat/choices.py
django_spire/ai/chat/message_intel.py
django_spire/ai/chat/models.py
django_spire/ai/chat/querysets.py
django_spire/ai/chat/responses.py
django_spire/ai/chat/router.py
django_spire/ai/chat/auth/__init__.py
django_spire/ai/chat/auth/controller.py
django_spire/ai/chat/intelligence/__init__.py
django_spire/ai/chat/intelligence/prompts.py
django_spire/ai/chat/intelligence/decoders/__init__.py
django_spire/ai/chat/intelligence/decoders/intent_decoder.py
django_spire/ai/chat/intelligence/workflows/__init__.py
django_spire/ai/chat/intelligence/workflows/chat_workflow.py
django_spire/ai/chat/migrations/0001_initial.py
django_spire/ai/chat/migrations/0002_remove_chatmessage_content_chatmessage__content_and_more.py
django_spire/ai/chat/migrations/0003_rename__content_chatmessage__intel_data_and_more.py
django_spire/ai/chat/migrations/0004_chatmessage_response_type_chatmessage_sender.py
django_spire/ai/chat/migrations/__init__.py
django_spire/ai/chat/templates/django_spire/ai/chat/card/chat_card.html
django_spire/ai/chat/templates/django_spire/ai/chat/dropdown/ellipsis_dropdown.html
django_spire/ai/chat/templates/django_spire/ai/chat/element/recent_chat_select_element.html
django_spire/ai/chat/templates/django_spire/ai/chat/message/default_message.html
django_spire/ai/chat/templates/django_spire/ai/chat/message/loading_response_message.html
django_spire/ai/chat/templates/django_spire/ai/chat/message/message.html
django_spire/ai/chat/templates/django_spire/ai/chat/message/request_message.html
django_spire-0.25.2.dist-info/licenses/LICENSE.md
django_spire-0.25.2.dist-info/METADATA
django_spire-0.25.2.dist-info/WHEEL
django_spire-0.25.2.dist-info/top_level.txt
django_spire-0.25.2.dist-info/RECORD
