Metadata-Version: 2.4
Name: django-spire
Version: 0.25.2
Summary: A project for Django Spire
Author-email: Brayden Carlson <braydenc@stratusadv.com>, Nathan Johnson <nathanj@stratusadv.com>
License: Copyright (c) 2025 Stratus Advanced Technologies and Contributors.
Keywords: portal,cmms,spire,django,backend,frontend,javascript,active server pages
Classifier: Development Status :: 5 - Production/Stable
Classifier: Environment :: Web Environment
Classifier: Framework :: Django
Classifier: Framework :: Django :: 3.2
Classifier: Framework :: Django :: 4.0
Classifier: License :: OSI Approved :: MIT License
Classifier: Operating System :: OS Independent
Classifier: Programming Language :: JavaScript
Classifier: Programming Language :: Python :: 3
Classifier: Programming Language :: Python :: 3.10
Classifier: Programming Language :: Python :: 3.11
Classifier: Programming Language :: Python :: 3.12
Classifier: Topic :: Internet :: WWW/HTTP
Classifier: Topic :: Internet :: WWW/HTTP :: Dynamic Content
Classifier: Topic :: Software Development :: Libraries :: Python Modules
Requires-Python: >=3.11
License-File: LICENSE.md
Requires-Dist: beautifulsoup4>=4.14.2
Requires-Dist: boto3>=1.34.0
Requires-Dist: botocore>=1.34.0
Requires-Dist: crispy-bootstrap5==2024.10
Requires-Dist: dandy>=1.3.5
Requires-Dist: django>=5.1.8
Requires-Dist: django-crispy-forms==2.3
Requires-Dist: django-glue>=0.8.12
Requires-Dist: django-sendgrid-v5
Requires-Dist: django-storages==1.14.5
Requires-Dist: docutils
Requires-Dist: faker
Requires-Dist: marko==2.1.4
Requires-Dist: markitdown[docx,pdf]==0.1.2
Requires-Dist: psycopg2
Requires-Dist: pydantic
Requires-Dist: Pygments
Requires-Dist: Pillow==11.2.1
Requires-Dist: python-dateutil
Requires-Dist: robit>=0.4.8
Requires-Dist: typing_extensions
Requires-Dist: twilio
Provides-Extra: development
Requires-Dist: build; extra == "development"
Requires-Dist: django-browser-reload; extra == "development"
Requires-Dist: django-debug-toolbar; extra == "development"
Requires-Dist: django-watchfiles; extra == "development"
Requires-Dist: pip; extra == "development"
Requires-Dist: playwright; extra == "development"
Requires-Dist: pyinstrument; extra == "development"
Requires-Dist: pyrefly; extra == "development"
Requires-Dist: pytest; extra == "development"
Requires-Dist: pytest-django; extra == "development"
Requires-Dist: pytest-playwright; extra == "development"
Requires-Dist: setuptools; extra == "development"
Requires-Dist: twine; extra == "development"
Provides-Extra: documentation
Requires-Dist: mkdocs; extra == "documentation"
Requires-Dist: markdown-exec[ansi]; extra == "documentation"
Requires-Dist: mkdocs-include-markdown-plugin; extra == "documentation"
Requires-Dist: mkdocs-material; extra == "documentation"
Requires-Dist: mkdocs-table-reader-plugin; extra == "documentation"
Requires-Dist: mkdocstrings-python; extra == "documentation"
Requires-Dist: mkdocs-gen-files; extra == "documentation"
Requires-Dist: mkdocs-literate-nav; extra == "documentation"
Requires-Dist: mkdocs-section-index; extra == "documentation"
Requires-Dist: openpyxl; extra == "documentation"
Dynamic: license-file
